MANIFEST.in
README.md
VERSION
setup.py
testnado/__init__.py
testnado/authenticated_fetch_case.py
testnado/fetch_case.py
testnado/handler_test_case.py
testnado/mock_client.py
testnado/mock_service.py
testnado/service_case_helpers.py
testnado.egg-info/PKG-INFO
testnado.egg-info/SOURCES.txt
testnado.egg-info/dependency_links.txt
testnado.egg-info/requires.txt
testnado.egg-info/top_level.txt
testnado/credentials/__init__.py
testnado/credentials/cookie_credentials.py
testnado/credentials/header_credentials.py
testnado/credentials/helpers.py
tests/credentials/__init__.py
tests/credentials/test_cookie_credentials.py
tests/credentials/test_credentials.py
tests/credentials/test_header_credentials.py
tests/credentials/test_helpers.py