Metadata-Version: 1.0
Name: testnado
Version: 1.0.1
Summary: Tornado test helpers and Selenium testing with Tornado
Home-page: http://github.com/joshmarshall/testnado/
Author: Josh Marshall
Author-email: catchjosh@gmail.com
License: http://www.apache.org/licenses/LICENSE-2.0
Platform: UNKNOWN
